README.md
setup.py
db_operations/__init__.py
db_operations.egg-info/PKG-INFO
db_operations.egg-info/SOURCES.txt
db_operations.egg-info/dependency_links.txt
db_operations.egg-info/not-zip-safe
db_operations.egg-info/requires.txt
db_operations.egg-info/top_level.txt
db_operations/db_query/__init__.py
db_operations/db_query/db_query.py
db_operations/pg_query/__init__.py
db_operations/pg_query/con_pgsql.py