Metadata-Version: 2.1
Name: db-operations
Version: 1.0.1
Summary: Simple operation of database
Home-page: https://github.com/kimkimheel/db_operations
Author: K.lz
Author-email: 565150134@qq.com
License: UNKNOWN
Platform: UNKNOWN
